[
  {
    "id": "wattenberg_viegas",
    "day": 25,
    "talk": 1,
    "keynote": true,
    "time": "9:15 - 10:00",
    "speakers": "Martin Wattenberg and Fernanda Viégas",
    "title": "Seeing Machines Think",
    "tfidf": [
      { "token": "robot", "score": 0.07405418595725911 },
      { "token": "one", "score": 0.053459870499677785 },
      { "token": "thing", "score": 0.053459870499677785 },
      { "token": "network", "score": 0.04936945730483941 },
      { "token": "system", "score": 0.0479336052000169 },
      { "token": "see", "score": 0.04200418396403255 },
      { "token": "node", "score": 0.0414703441360651 },
      { "token": "cat", "score": 0.0391577235843656 },
      { "token": "data", "score": 0.03914026233012124 },
      { "token": "airplan", "score": 0.034791268310102624 },
      { "token": "look", "score": 0.033412419062298616 },
      { "token": "go", "score": 0.033412419062298616 },
      { "token": "like", "score": 0.033412419062298616 },
      { "token": "neural", "score": 0.03258384182119401 },
      { "token": "neuron", "score": 0.031312141479092365 },
      { "token": "layer", "score": 0.03118735456013226 },
      { "token": "okay", "score": 0.030753238993557523 },
      { "token": "right", "score": 0.030609063529000433 },
      { "token": "wine", "score": 0.029621674382903643 },
      { "token": "imag", "score": 0.028645755543809465 },
      { "token": "weight", "score": 0.02818219872798943 },
      { "token": "machin", "score": 0.02764689609071007 },
      { "token": "net", "score": 0.02665950694461328 },
      { "token": "differ", "score": 0.02577529470520179 },
      { "token": "play", "score": 0.02479989160343155 },
      { "token": "let", "score": 0.024684728652419705 },
      { "token": "white", "score": 0.02349463415061936 },
      { "token": "sort", "score": 0.02268982139271285 },
      { "token": "think", "score": 0.021956732526653377 },
      { "token": "start", "score": 0.02172256121412934 },
      { "token": "want", "score": 0.021002091982016274 },
      { "token": "pictur", "score": 0.020951890953538898 },
      { "token": "graph", "score": 0.02017437715598108 },
      { "token": "two", "score": 0.020047451437379172 },
      { "token": "visual", "score": 0.020047451437379172 },
      { "token": "featur", "score": 0.019774826481506594 },
      { "token": "talk", "score": 0.019747782921935762 },
      { "token": "point", "score": 0.019747782921935762 },
      { "token": "comput", "score": 0.019107218014916084 },
      { "token": "get", "score": 0.019092810892742066 },
      { "token": "realli", "score": 0.019092810892742066 },
      { "token": "input", "score": 0.018345502682430744 },
      { "token": "frog", "score": 0.018273604339370614 },
      { "token": "tensor", "score": 0.017773004629742187 },
      { "token": "trim", "score": 0.017395634155051312 },
      { "token": "rorschach", "score": 0.017395634155051312 },
      { "token": "someth", "score": 0.017183529803467858 },
      { "token": "take", "score": 0.0167856154836454 },
      { "token": "learn", "score": 0.016718815763051575 },
      { "token": "neg", "score": 0.0164396159246605 }
    ]
  },
  {
    "id": "mcdonald",
    "day": 25,
    "talk": 2,
    "time": "10:00 - 10:30",
    "speakers": "Kyle McDonald",
    "title": "A Return to Machine Learning",
    "tfidf": [
      { "token": "net", "score": 0.060072755648528584 },
      { "token": "neural", "score": 0.03234686842613078 },
      { "token": "like", "score": 0.02531706724377598 },
      { "token": "imag", "score": 0.02234368932417138 },
      { "token": "deepdream", "score": 0.020794415416798356 },
      { "token": "categori", "score": 0.018325814637483104 },
      { "token": "go", "score": 0.017126251370789634 },
      { "token": "look", "score": 0.015637012121155754 },
      { "token": "one", "score": 0.015637012121155754 },
      { "token": "output", "score": 0.014654743338554503 },
      { "token": "research", "score": 0.014237875066684749 },
      { "token": "face", "score": 0.013862943611198907 },
      { "token": "ai", "score": 0.013862943611198907 },
      { "token": "smile", "score": 0.013862943611198907 },
      { "token": "train", "score": 0.013369576860233549 },
      { "token": "feed", "score": 0.01282290042123519 },
      { "token": "see", "score": 0.01265853362188799 },
      { "token": "word", "score": 0.012364011142736976 },
      { "token": "post", "score": 0.012322616543287916 },
      { "token": "learn", "score": 0.012109199416953069 },
      { "token": "thing", "score": 0.011913913997071049 },
      { "token": "tri", "score": 0.011552453009332421 },
      { "token": "use", "score": 0.01116929437225411 },
      { "token": "digit", "score": 0.010991057503915878 },
      { "token": "t-sne", "score": 0.010854875712752019 },
      { "token": "recurr", "score": 0.010854875712752019 },
      { "token": "last", "score": 0.010753029082574942 },
      { "token": "differ", "score": 0.010424674747437168 },
      { "token": "dimension", "score": 0.010181008131935057 },
      { "token": "style", "score": 0.010027182645175162 },
      { "token": "work", "score": 0.009680055122620228 },
      { "token": "start", "score": 0.009241962407465937 },
      { "token": "network", "score": 0.009241962407465937 },
      { "token": "take", "score": 0.009241962407465937 },
      { "token": "toolkit", "score": 0.009159214586596565 },
      { "token": "next", "score": 0.008937475729668553 },
      { "token": "make", "score": 0.008935435497803288 },
      { "token": "data", "score": 0.008935435497803288 },
      { "token": "familiar", "score": 0.008585695255377588 },
      { "token": "similar", "score": 0.008545877041374442 },
      { "token": "vector", "score": 0.008355985537645967 },
      { "token": "techniqu", "score": 0.00830542712223277 },
      { "token": "think", "score": 0.008190815872986347 },
      { "token": "python", "score": 0.008144806505548045 },
      { "token": "caption", "score": 0.008141156784564015 },
      { "token": "puppi", "score": 0.008141156784564015 },
      { "token": "chat", "score": 0.008141156784564015 },
      { "token": "convnet", "score": 0.008141156784564015 },
      { "token": "slug", "score": 0.008141156784564015 },
      { "token": "first", "score": 0.007975997701670186 }
    ]
  },
  {
    "id": "kosaka",
    "day": 25,
    "talk": 3,
    "time": "11:00 - 11:30",
    "speakers": "Mariko Kosaka",
    "title": "Drawing on <canvas> - how computers read pixels",
    "tfidf": [
      { "token": "imag", "score": 0.08984268796316032 },
      { "token": "canva", "score": 0.07258085660313562 },
      { "token": "like", "score": 0.060817100246828654 },
      { "token": "pixel", "score": 0.04622583192874449 },
      { "token": "get", "score": 0.044443265564990175 },
      { "token": "worker", "score": 0.039919471131724595 },
      { "token": "use", "score": 0.03742590784420225 },
      { "token": "data", "score": 0.03742590784420225 },
      { "token": "blur", "score": 0.03629042830156781 },
      { "token": "jpeg", "score": 0.034099086008645085 },
      { "token": "creat", "score": 0.030242023584639847 },
      { "token": "kind", "score": 0.02923899050328301 },
      { "token": "color", "score": 0.027283158767709276 },
      { "token": "want", "score": 0.025730311642889046 },
      { "token": "gif", "score": 0.025574314506483817 },
      { "token": "transpar", "score": 0.022387557148757717 },
      { "token": "thread", "score": 0.022387557148757717 },
      { "token": "know", "score": 0.022221632782495088 },
      { "token": "png", "score": 0.02177425698094069 },
      { "token": "lightbulb", "score": 0.02131192875540318 },
      { "token": "knit", "score": 0.02131192875540318 },
      { "token": "go", "score": 0.019882513542232447 },
      { "token": "one", "score": 0.019882513542232447 },
      { "token": "javascript", "score": 0.018910567607213654 },
      { "token": "ui", "score": 0.018374418459745058 },
      { "token": "slope", "score": 0.018145214150783906 },
      { "token": "put", "score": 0.017543394301969804 },
      { "token": "friend", "score": 0.016935533207398313 },
      { "token": "make", "score": 0.016373834681838485 },
      { "token": "invert", "score": 0.015991112249112656 },
      { "token": "photo", "score": 0.015991112249112656 },
      { "token": "contrast", "score": 0.015749501536924337 },
      { "token": "fulli", "score": 0.015749501536924337 },
      { "token": "element", "score": 0.015732949420848984 },
      { "token": "array", "score": 0.015732949420848984 },
      { "token": "number", "score": 0.01572585226401272 },
      { "token": "take", "score": 0.01572585226401272 },
      { "token": "event", "score": 0.014708219250055065 },
      { "token": "machin", "score": 0.014516171320627127 },
      { "token": "tweet", "score": 0.014516171320627125 },
      { "token": "languag", "score": 0.01412357293791944 },
      { "token": "context", "score": 0.013821666283486394 },
      { "token": "call", "score": 0.013780519589273097 },
      { "token": "process", "score": 0.013750817864197379 },
      { "token": "twitter", "score": 0.013485385217870557 },
      { "token": "give", "score": 0.012991980365575846 },
      { "token": "someth", "score": 0.012865155821444523 },
      { "token": "html", "score": 0.012792889799290124 },
      { "token": "util", "score": 0.012792889799290124 },
      { "token": "css", "score": 0.012792889799290124 }
    ]
  },
  {
    "id": "case",
    "day": 25,
    "talk": 4,
    "time": "11:30 - 12:00",
    "speakers": "Nicky Case",
    "title": "How To Simulate The Universe, In 134 Easy Steps",
    "tfidf": [
      { "token": "system", "score": 0.07041726037455397 },
      { "token": "simul", "score": 0.06026426338185774 },
      { "token": "like", "score": 0.036062295731044657 },
      { "token": "stori", "score": 0.034241058739691896 },
      { "token": "think", "score": 0.031053643546177342 },
      { "token": "loop", "score": 0.029227213988178718 },
      { "token": "stock", "score": 0.02797454988806954 },
      { "token": "flow", "score": 0.026994905926590495 },
      { "token": "water", "score": 0.024866266567172925 },
      { "token": "one", "score": 0.024041530487363103 },
      { "token": "thing", "score": 0.02303980005038964 },
      { "token": "peopl", "score": 0.02203806961341618 },
      { "token": "discrimin", "score": 0.021904457716315735 },
      { "token": "loopi", "score": 0.02175798324627631 },
      { "token": "inform", "score": 0.021302834434791532 },
      { "token": "model", "score": 0.02075026635279167 },
      { "token": "affect", "score": 0.020721888805977435 },
      { "token": "individu", "score": 0.020294208277867275 },
      { "token": "caus", "score": 0.020234225068739117 },
      { "token": "go", "score": 0.019032878302495792 },
      { "token": "empathi", "score": 0.018649699925379692 },
      { "token": "causal", "score": 0.018649699925379692 },
      { "token": "viciou", "score": 0.018649699925379692 },
      { "token": "neighborhood", "score": 0.018649699925379692 },
      { "token": "incarcer", "score": 0.018253714763596444 },
      { "token": "empow", "score": 0.018253714763596444 },
      { "token": "ex-con", "score": 0.018253714763596444 },
      { "token": "linear", "score": 0.017985977838879213 },
      { "token": "realli", "score": 0.017029417428548865 },
      { "token": "least", "score": 0.016577511044781952 },
      { "token": "use", "score": 0.016027686991575404 },
      { "token": "theori", "score": 0.015737730609019313 },
      { "token": "polar", "score": 0.015541416604483077 },
      { "token": "b", "score": 0.015541416604483077 },
      { "token": "tell", "score": 0.015024616662235073 },
      { "token": "cycl", "score": 0.014786176014236607 },
      { "token": "non-linear", "score": 0.014602971810877156 },
      { "token": "cray", "score": 0.014602971810877156 },
      { "token": "addict", "score": 0.014602971810877156 },
      { "token": "inventori", "score": 0.014602971810877156 },
      { "token": "unhappi", "score": 0.014602971810877156 },
      { "token": "agent-bas", "score": 0.014602971810877156 },
      { "token": "prototyp", "score": 0.014505322164184207 },
      { "token": "also", "score": 0.014505322164184207 },
      { "token": "us", "score": 0.01446595840705149 },
      { "token": "break", "score": 0.014397283160848266 },
      { "token": "get", "score": 0.014024226117628477 },
      { "token": "know", "score": 0.014024226117628477 },
      { "token": "stat", "score": 0.013696423495876757 },
      { "token": "media", "score": 0.013696423495876757 }
    ]
  },
  {
    "id": "mcnamara",
    "day": 25,
    "talk": 5,
    "time": "12:00 - 12:30",
    "speakers": "Amelia McNamara",
    "title": "Do you know Nothing when you see it?",
    "tfidf": [
      { "token": "differ", "score": 0.06898681818156949 },
      { "token": "ant", "score": 0.056440792834162284 },
      { "token": "distribut", "score": 0.05195352811724942 },
      { "token": "plot", "score": 0.04887987598446437 },
      { "token": "statist", "score": 0.048700372246889674 },
      { "token": "observ", "score": 0.04739739695723553 },
      { "token": "bootstrap", "score": 0.04368574667394613 },
      { "token": "random", "score": 0.04077336356234972 },
      { "token": "could", "score": 0.03931717200655152 },
      { "token": "one", "score": 0.0380131447122934 },
      { "token": "data", "score": 0.03660525046368994 },
      { "token": "inch", "score": 0.03591686816719418 },
      { "token": "height", "score": 0.033276532690914726 },
      { "token": "loan", "score": 0.030785887000452157 },
      { "token": "tug", "score": 0.030785887000452157 },
      { "token": "lineup", "score": 0.030785887000452157 },
      { "token": "like", "score": 0.029565779220672644 },
      { "token": "realli", "score": 0.028157884972069183 },
      { "token": "think", "score": 0.028157884972069183 },
      { "token": "noth", "score": 0.02762775599121899 },
      { "token": "go", "score": 0.025342096474862262 },
      { "token": "standard", "score": 0.02424497978804973 },
      { "token": "look", "score": 0.023934202226258805 },
      { "token": "see", "score": 0.023934202226258805 },
      { "token": "polygon", "score": 0.023099766349768618 },
      { "token": "war", "score": 0.023099766349768618 },
      { "token": "use", "score": 0.022526307977655344 },
      { "token": "want", "score": 0.022526307977655344 },
      { "token": "default", "score": 0.022118785246709915 },
      { "token": "make", "score": 0.021118413729051887 },
      { "token": "neg", "score": 0.020781411246899768 },
      { "token": "decrypt", "score": 0.0205239246669681 },
      { "token": "three-quart", "score": 0.0205239246669681 },
      { "token": "null", "score": 0.0205239246669681 },
      { "token": "number", "score": 0.02038668178117486 },
      { "token": "possibl", "score": 0.020231420401035503 },
      { "token": "group", "score": 0.019249805291473847 },
      { "token": "histogram", "score": 0.018939033651568207 },
      { "token": "know", "score": 0.01830262523184497 },
      { "token": "valu", "score": 0.017867833551614077 },
      { "token": "real", "score": 0.01732482476232646 },
      { "token": "sampl", "score": 0.01731784270574981 },
      { "token": "relationship", "score": 0.016233457415629895 },
      { "token": "comput", "score": 0.015850762003445353 },
      { "token": "team", "score": 0.01570353867649053 },
      { "token": "thing", "score": 0.01548683673463805 },
      { "token": "two", "score": 0.01548683673463805 },
      { "token": "bin", "score": 0.015399844233179076 },
      { "token": "aran", "score": 0.015392943500226079 },
      { "token": "infer", "score": 0.015392943500226079 }
    ]
  },
  {
    "id": "bremer",
    "day": 25,
    "talk": 6,
    "time": "2:00 - 2:30",
    "speakers": "Nadieh Bremer",
    "title": "SVG Beyond Mere Shapes",
    "tfidf": [
      { "token": "gradient", "score": 0.10375132957425932 },
      { "token": "blur", "score": 0.05297940233579199 },
      { "token": "color", "score": 0.04860200553001168 },
      { "token": "data", "score": 0.034148161138101735 },
      { "token": "use", "score": 0.03201390106697038 },
      { "token": "one", "score": 0.03201390106697038 },
      { "token": "visual", "score": 0.028812510960273336 },
      { "token": "glow", "score": 0.027223613451567562 },
      { "token": "want", "score": 0.02454399081801062 },
      { "token": "circl", "score": 0.02449455202941719 },
      { "token": "set", "score": 0.02428222607057133 },
      { "token": "stop", "score": 0.023005849764189863 },
      { "token": "effect", "score": 0.023005849764189863 },
      { "token": "thing", "score": 0.022409730746879263 },
      { "token": "filter", "score": 0.022104981194295586 },
      { "token": "creat", "score": 0.022074750973246664 },
      { "token": "rectangl", "score": 0.02100202070811951 },
      { "token": "chord", "score": 0.02042686344942384 },
      { "token": "make", "score": 0.020275470675747906 },
      { "token": "occup", "score": 0.019445438179691115 },
      { "token": "cord", "score": 0.019445438179691115 },
      { "token": "aveng", "score": 0.019445438179691115 },
      { "token": "svg", "score": 0.018456510501209784 },
      { "token": "well", "score": 0.018288911927396605 },
      { "token": "start", "score": 0.017659800778597332 },
      { "token": "work", "score": 0.01600695053348519 },
      { "token": "see", "score": 0.01600695053348519 },
      { "token": "although", "score": 0.01575151553108963 },
      { "token": "outward", "score": 0.015556350543752893 },
      { "token": "appear", "score": 0.015452325681272664 },
      { "token": "result", "score": 0.015303448519127716 },
      { "token": "locat", "score": 0.015303448519127716 },
      { "token": "go", "score": 0.014939820497919507 },
      { "token": "like", "score": 0.014939820497919507 },
      { "token": "move", "score": 0.01485974094100974 },
      { "token": "blend", "score": 0.014590616749588456 },
      { "token": "star", "score": 0.014370166211238287 },
      { "token": "percentag", "score": 0.013244850583947998 },
      { "token": "window", "score": 0.013244850583947998 },
      { "token": "re-creat", "score": 0.013244850583947998 },
      { "token": "append", "score": 0.013244850583947998 },
      { "token": "educ", "score": 0.013126262942574695 },
      { "token": "mimic", "score": 0.013126262942574695 },
      { "token": "chang", "score": 0.012573626950085166 },
      { "token": "screen", "score": 0.012546526490740603 },
      { "token": "direct", "score": 0.012546526490740603 },
      { "token": "point", "score": 0.012141113035285665 },
      { "token": "countri", "score": 0.01197513850936524 },
      { "token": "show", "score": 0.01173843039122247 },
      { "token": "accid", "score": 0.011672493399670766 }
    ]
  },
  {
    "id": "vivo",
    "day": 25,
    "talk": 7,
    "time": "2:30 - 3:15",
    "speakers": "Patricio Gonzalez Vivo",
    "title": "Enhancing your maps and visualizations with WebGL GLSL Shaders",
    "tfidf": [
      { "token": "go", "score": 0.04761333302559478 },
      { "token": "like", "score": 0.04642299969995491 },
      { "token": "satellit", "score": 0.04432202220276737 },
      { "token": "shader", "score": 0.0433809420136626 },
      { "token": "pixel", "score": 0.03849291381503881 },
      { "token": "one", "score": 0.03690033309483596 },
      { "token": "make", "score": 0.033329333117916346 },
      { "token": "card", "score": 0.029548014801844914 },
      { "token": "inform", "score": 0.023824630633163573 },
      { "token": "right", "score": 0.02339217838479389 },
      { "token": "comput", "score": 0.02233559121859085 },
      { "token": "pipe", "score": 0.022161011101383684 },
      { "token": "pass", "score": 0.022161011101383684 },
      { "token": "cpu", "score": 0.0216904710068313 },
      { "token": "tangram", "score": 0.0216904710068313 },
      { "token": "put", "score": 0.02142599986151765 },
      { "token": "let", "score": 0.02092984381797348 },
      { "token": "work", "score": 0.020235666535877782 },
      { "token": "use", "score": 0.020235666535877782 },
      { "token": "want", "score": 0.020235666535877782 },
      { "token": "build", "score": 0.02021508629769218 },
      { "token": "per", "score": 0.019530175457353218 },
      { "token": "see", "score": 0.01785499988459804 },
      { "token": "memori", "score": 0.017570074162565348 },
      { "token": "engin", "score": 0.017236341967742867 },
      { "token": "imag", "score": 0.017144713655492073 },
      { "token": "imagin", "score": 0.0170765749050555 },
      { "token": "thing", "score": 0.016664666558958173 },
      { "token": "graphic", "score": 0.016275146214461012 },
      { "token": "wind", "score": 0.016275146214461012 },
      { "token": "station", "score": 0.016275146214461012 },
      { "token": "data", "score": 0.015474333233318304 },
      { "token": "bottl", "score": 0.014774007400922457 },
      { "token": "get", "score": 0.014283999907678434 },
      { "token": "someth", "score": 0.014283999907678434 },
      { "token": "look", "score": 0.014283999907678434 },
      { "token": "lot", "score": 0.014283999907678434 },
      { "token": "know", "score": 0.014283999907678434 },
      { "token": "channel", "score": 0.013724912486394012 },
      { "token": "realtim", "score": 0.013020116971568811 },
      { "token": "geometri", "score": 0.013020116971568811 },
      { "token": "ping-pong", "score": 0.01301428260409878 },
      { "token": "privileg", "score": 0.01301428260409878 },
      { "token": "st", "score": 0.01301428260409878 },
      { "token": "flash", "score": 0.01301428260409878 },
      { "token": "mapzen", "score": 0.01301428260409878 },
      { "token": "server", "score": 0.01301428260409878 },
      { "token": "present", "score": 0.012830971271679604 },
      { "token": "code", "score": 0.012440053106272112 },
      { "token": "gradient", "score": 0.012311672834102047 }
    ]
  },
  {
    "id": "armstrong",
    "day": 25,
    "talk": 8,
    "time": "4:00 - 4:30",
    "speakers": "Zan Armstrong",
    "title": "Everything is Seasonal",
    "tfidf": [
      { "token": "season", "score": 0.15816923347827677 },
      { "token": "week", "score": 0.06629016928580303 },
      { "token": "day", "score": 0.05489060175267188 },
      { "token": "data", "score": 0.05285469658298819 },
      { "token": "month", "score": 0.04209085236202011 },
      { "token": "see", "score": 0.03889307861767056 },
      { "token": "look", "score": 0.03889307861767056 },
      { "token": "year", "score": 0.038164353691544604 },
      { "token": "growth", "score": 0.035451724745131 },
      { "token": "babi", "score": 0.03434705469973712 },
      { "token": "summer", "score": 0.03094407056071184 },
      { "token": "pattern", "score": 0.028613427593887637 },
      { "token": "weekend", "score": 0.027270557496254615 },
      { "token": "time", "score": 0.02592871907844704 },
      { "token": "long-term", "score": 0.025441114951762545 },
      { "token": "born", "score": 0.024543501746629153 },
      { "token": "increas", "score": 0.024533610499812224 },
      { "token": "aggreg", "score": 0.02299739800547568 },
      { "token": "wednesday", "score": 0.02180666995865361 },
      { "token": "april", "score": 0.02180666995865361 },
      { "token": "monthli", "score": 0.02180666995865361 },
      { "token": "saturday", "score": 0.021660849392498287 },
      { "token": "sale", "score": 0.021660849392498287 },
      { "token": "compar", "score": 0.01970788816604955 },
      { "token": "go", "score": 0.01894791009578822 },
      { "token": "seri", "score": 0.018566442336427104 },
      { "token": "friday", "score": 0.018566442336427104 },
      { "token": "behavior", "score": 0.018172224965544673 },
      { "token": "2016", "score": 0.018172224965544673 },
      { "token": "peak", "score": 0.018172224965544673 },
      { "token": "gun", "score": 0.018172224965544673 },
      { "token": "differ", "score": 0.017950651669694104 },
      { "token": "number", "score": 0.016503504299046314 },
      { "token": "period", "score": 0.016503504299046314 },
      { "token": "set", "score": 0.016503504299046314 },
      { "token": "let", "score": 0.016503504299046314 },
      { "token": "per", "score": 0.01636233449775277 },
      { "token": "trend", "score": 0.016124635772222357 },
      { "token": "chang", "score": 0.016023209668533857 },
      { "token": "two", "score": 0.01595613481750587 },
      { "token": "want", "score": 0.01595613481750587 },
      { "token": "monday", "score": 0.01547203528035592 },
      { "token": "chart", "score": 0.015053584995215474 },
      { "token": "variat", "score": 0.014720166299887335 },
      { "token": "factor", "score": 0.014720166299887335 },
      { "token": "thursday", "score": 0.014537779972435739 },
      { "token": "tuesday", "score": 0.014537779972435739 },
      { "token": "appl", "score": 0.014537779972435739 },
      { "token": "patio", "score": 0.014537779972435739 },
      { "token": "tractor", "score": 0.014537779972435739 }
    ]
  },
  {
    "id": "wu",
    "day": 25,
    "talk": 9,
    "time": "4:30 - 5:00",
    "speakers": "Shirley Wu",
    "title": "Building Data Visualizations for Product",
    "tfidf": [
      { "token": "custom", "score": 0.09018303592956617 },
      { "token": "illumin", "score": 0.05638712196148647 },
      { "token": "workflow", "score": 0.045091517964783084 },
      { "token": "data", "score": 0.043531608835451915 },
      { "token": "realli", "score": 0.035512628260500244 },
      { "token": "action", "score": 0.03381863847358731 },
      { "token": "user", "score": 0.03292361063553127 },
      { "token": "optim", "score": 0.031991408333535934 },
      { "token": "product", "score": 0.031126181897799383 },
      { "token": "us", "score": 0.030541147690153682 },
      { "token": "layout", "score": 0.029224665380486205 },
      { "token": "visual", "score": 0.027493647685548576 },
      { "token": "oftentim", "score": 0.02504971318327389 },
      { "token": "start", "score": 0.022512472531006772 },
      { "token": "recalcul", "score": 0.02192832520724474 },
      { "token": "figur", "score": 0.02192832520724474 },
      { "token": "much", "score": 0.021765804417725958 },
      { "token": "use", "score": 0.020620235764161433 },
      { "token": "learn", "score": 0.02006257891566189 },
      { "token": "know", "score": 0.019474667110596908 },
      { "token": "need", "score": 0.01895787160505833 },
      { "token": "room", "score": 0.01895787160505833 },
      { "token": "forc", "score": 0.01879570732049549 },
      { "token": "lesson", "score": 0.01879570732049549 },
      { "token": "feedback", "score": 0.01879570732049549 },
      { "token": "calcul", "score": 0.018522658528091325 },
      { "token": "like", "score": 0.018329098457032383 },
      { "token": "traffic", "score": 0.017997507311852855 },
      { "token": "import", "score": 0.017874951459337107 },
      { "token": "number", "score": 0.017773004629742187 },
      { "token": "go", "score": 0.017183529803467858 },
      { "token": "one", "score": 0.017183529803467858 },
      { "token": "first", "score": 0.017179071972828093 },
      { "token": "could", "score": 0.016588137654426044 },
      { "token": "build", "score": 0.016461805317765636 },
      { "token": "surprisingli", "score": 0.015663089433746242 },
      { "token": "meant", "score": 0.015426434838731016 },
      { "token": "talk", "score": 0.015403270679109895 },
      { "token": "abl", "score": 0.014965277561605128 },
      { "token": "team", "score": 0.014602948786343332 },
      { "token": "featur", "score": 0.014602948786343332 },
      { "token": "applic", "score": 0.01421840370379375 },
      { "token": "support", "score": 0.014091099363994716 },
      { "token": "thing", "score": 0.013746823842774288 },
      { "token": "lot", "score": 0.013746823842774288 },
      { "token": "keep", "score": 0.013468749805444614 },
      { "token": "slow", "score": 0.012855362365609182 },
      { "token": "time", "score": 0.012601255189209763 },
      { "token": "work", "score": 0.012601255189209763 },
      { "token": "alon", "score": 0.012530471546996992 }
    ]
  },
  {
    "id": "chu",
    "day": 25,
    "talk": 10,
    "time": "5:00 - 5:45",
    "speakers": "Tony Hang Shing Chu",
    "title": "Animation, Pacing, and Exposition",
    "tfidf": [
      { "token": "attent", "score": 0.12266892723320859 },
      { "token": "idea", "score": 0.07294244228617754 },
      { "token": "thing", "score": 0.06954466307252559 },
      { "token": "like", "score": 0.04931348836051814 },
      { "token": "tree", "score": 0.04840781224995536 },
      { "token": "right", "score": 0.04446604554535498 },
      { "token": "pace", "score": 0.039234746069430865 },
      { "token": "motion", "score": 0.03803470962496493 },
      { "token": "go", "score": 0.035404555746013026 },
      { "token": "design", "score": 0.03321681697828926 },
      { "token": "drain", "score": 0.0322574136746876 },
      { "token": "head", "score": 0.03202081447616323 },
      { "token": "piec", "score": 0.030538895446897505 },
      { "token": "kind", "score": 0.030346762068011162 },
      { "token": "scroll", "score": 0.027661606999974494 },
      { "token": "think", "score": 0.0252889683900093 },
      { "token": "one", "score": 0.0252889683900093 },
      { "token": "oh", "score": 0.024777417094921695 },
      { "token": "depend", "score": 0.02348193061585303 },
      { "token": "lego", "score": 0.023041009767634003 },
      { "token": "brain", "score": 0.02186922376369763 },
      { "token": "someth", "score": 0.021495623131507907 },
      { "token": "fit", "score": 0.02074620524998087 },
      { "token": "decis", "score": 0.020147936415119926 },
      { "token": "introduc", "score": 0.019617373034715432 },
      { "token": "hey", "score": 0.01943931001217567 },
      { "token": "visual", "score": 0.018966726292506977 },
      { "token": "exposit", "score": 0.018664059912309978 },
      { "token": "reconstruct", "score": 0.0184328078141072 },
      { "token": "elev", "score": 0.0184328078141072 },
      { "token": "break", "score": 0.01817317440491979 },
      { "token": "order", "score": 0.018139833342540088 },
      { "token": "use", "score": 0.017702277873006513 },
      { "token": "stuff", "score": 0.017288504374984057 },
      { "token": "graphic", "score": 0.017288504374984057 },
      { "token": "deal", "score": 0.017288504374984057 },
      { "token": "anim", "score": 0.016518278063281128 },
      { "token": "first", "score": 0.016252976448686417 },
      { "token": "view", "score": 0.016118349132095942 },
      { "token": "talk", "score": 0.015693898427772347 },
      { "token": "short-term", "score": 0.015693898427772347 },
      { "token": "fun", "score": 0.015559653937485653 },
      { "token": "time", "score": 0.015173381034005581 },
      { "token": "guy", "score": 0.014943046755542838 },
      { "token": "screen", "score": 0.014866450256953016 },
      { "token": "need", "score": 0.014386073558791316 },
      { "token": "get", "score": 0.013908932614505116 },
      { "token": "data", "score": 0.013908932614505116 },
      { "token": "compos", "score": 0.0138246058605804 },
      { "token": "extens", "score": 0.0138246058605804 }
    ]
  },
  {
    "id": "chalabi",
    "day": 26,
    "talk": 1,
    "keynote": true,
    "time": "9:15 - 10:00",
    "speakers": "Mona Chalabi",
    "title": "Informing Without Alienating",
    "tfidf": [
      { "token": "data", "score": 0.0421241959182155 },
      { "token": "peopl", "score": 0.04020945974011479 },
      { "token": "iraqi", "score": 0.03489067193384578 },
      { "token": "iraq", "score": 0.0314016047404612 },
      { "token": "one", "score": 0.028721042671510565 },
      { "token": "realli", "score": 0.028721042671510565 },
      { "token": "think", "score": 0.028721042671510565 },
      { "token": "prison", "score": 0.02791253754707662 },
      { "token": "visual", "score": 0.025848938404359506 },
      { "token": "photograph", "score": 0.024423470353692044 },
      { "token": "chart", "score": 0.02312230655265097 },
      { "token": "way", "score": 0.022976834137208454 },
      { "token": "reader", "score": 0.021486819953946773 },
      { "token": "abus", "score": 0.021197039471837764 },
      { "token": "kind", "score": 0.02106209795910775 },
      { "token": "import", "score": 0.02068387240294722 },
      { "token": "super", "score": 0.01782378464297002 },
      { "token": "alien", "score": 0.01744533596692289 },
      { "token": "see", "score": 0.01723262560290634 },
      { "token": "time", "score": 0.01723262560290634 },
      { "token": "thing", "score": 0.01723262560290634 },
      { "token": "could", "score": 0.016833574385027243 },
      { "token": "get", "score": 0.016275257513855987 },
      { "token": "want", "score": 0.016275257513855987 },
      { "token": "subject", "score": 0.014853153869141683 },
      { "token": "look", "score": 0.014360521335755282 },
      { "token": "say", "score": 0.013825323106167783 },
      { "token": "like", "score": 0.013403153246704932 },
      { "token": "whether", "score": 0.012930309845612577 },
      { "token": "countri", "score": 0.012892091972368064 },
      { "token": "comment", "score": 0.012892091972368064 },
      { "token": "explain", "score": 0.012878542883066382 },
      { "token": "commun", "score": 0.012506696247912855 },
      { "token": "talk", "score": 0.011882523095313348 },
      { "token": "critic", "score": 0.011882523095313346 },
      { "token": "question", "score": 0.011780880838381995 },
      { "token": "opportun", "score": 0.011776133039909868 },
      { "token": "publish", "score": 0.011314021114911007 },
      { "token": "bad", "score": 0.011314021114911007 },
      { "token": "mani", "score": 0.011280339606647836 },
      { "token": "fact", "score": 0.011038751042628327 },
      { "token": "understand", "score": 0.01089231283737057 },
      { "token": "hundr", "score": 0.010743409976973387 },
      { "token": "interest", "score": 0.010634863927821371 },
      { "token": "go", "score": 0.010531048979553875 },
      { "token": "much", "score": 0.010531048979553875 },
      { "token": "fivethirtyeight", "score": 0.010471894078561772 },
      { "token": "electr", "score": 0.010471894078561772 },
      { "token": "divorc", "score": 0.010467201580153733 },
      { "token": "refuge", "score": 0.010467201580153733 }
    ]
  },
  {
    "id": "yanofsky",
    "day": 26,
    "talk": 2,
    "time": "10:00 - 10:30",
    "speakers": "David Yanofsky",
    "title": "The Charting Monster that Spawned from the Jaws of Defeat",
    "tfidf": [
      { "token": "chart", "score": 0.09748444804484561 },
      { "token": "chartbuild", "score": 0.05015878587646075 },
      { "token": "make", "score": 0.04658283908807401 },
      { "token": "quartz", "score": 0.042442049587774484 },
      { "token": "like", "score": 0.03599583020442083 },
      { "token": "know", "score": 0.03387842842769019 },
      { "token": "shark", "score": 0.032850577277722524 },
      { "token": "would", "score": 0.030660538792541023 },
      { "token": "tank", "score": 0.02956551954995027 },
      { "token": "use", "score": 0.027526223097498276 },
      { "token": "peopl", "score": 0.021174017767306368 },
      { "token": "react", "score": 0.02083612796950877 },
      { "token": "time", "score": 0.02011531687894105 },
      { "token": "client", "score": 0.01929184072171567 },
      { "token": "dad", "score": 0.015433472577372539 },
      { "token": "report", "score": 0.015330269396270512 },
      { "token": "tool", "score": 0.01528866694204968 },
      { "token": "code", "score": 0.015213516762863978 },
      { "token": "thing", "score": 0.014821812437114458 },
      { "token": "want", "score": 0.014821812437114458 },
      { "token": "stuff", "score": 0.014475367012229937 },
      { "token": "emb", "score": 0.014475367012229937 },
      { "token": "hour", "score": 0.014298920840329864 },
      { "token": "colleagu", "score": 0.014241674594228227 },
      { "token": "abl", "score": 0.013830469784421798 },
      { "token": "offic", "score": 0.013140230911089009 },
      { "token": "mobil", "score": 0.013140230911089009 },
      { "token": "path", "score": 0.013022579980942982 },
      { "token": "d3", "score": 0.012784845645225654 },
      { "token": "anyway", "score": 0.012207149652195623 },
      { "token": "start", "score": 0.012045211668498259 },
      { "token": "style", "score": 0.011880548157790475 },
      { "token": "axi", "score": 0.011808664154833321 },
      { "token": "one", "score": 0.011645709772018502 },
      { "token": "look", "score": 0.011645709772018502 },
      { "token": "export", "score": 0.011580293609783951 },
      { "token": "captiv", "score": 0.011575104433029405 },
      { "token": "ritchi", "score": 0.011575104433029405 },
      { "token": "anniversari", "score": 0.011575104433029405 },
      { "token": "fish", "score": 0.011575104433029405 },
      { "token": "penguin", "score": 0.011575104433029405 },
      { "token": "newspap", "score": 0.011575104433029405 },
      { "token": "chang", "score": 0.011340281092422065 },
      { "token": "text", "score": 0.011186739939572447 },
      { "token": "built", "score": 0.0107241906302474 },
      { "token": "wast", "score": 0.009855173183316758 },
      { "token": "wild", "score": 0.009855173183316758 },
      { "token": "melt", "score": 0.009855173183316758 },
      { "token": "great", "score": 0.009771752141971336 },
      { "token": "get", "score": 0.009528307995287866 }
    ]
  },
  {
    "id": "elliott",
    "day": 26,
    "talk": 3,
    "time": "11:00 - 11:30",
    "speakers": "Kennedy Elliott",
    "title": "Everything we know about how humans interpret graphics",
    "tfidf": [
      { "token": "chart", "score": 0.07986322986935367 },
      { "token": "particip", "score": 0.06116004534352458 },
      { "token": "pie", "score": 0.04506529656891285 },
      { "token": "bar", "score": 0.04167107226057197 },
      { "token": "studi", "score": 0.032884859357969164 },
      { "token": "found", "score": 0.032525154328937454 },
      { "token": "proport", "score": 0.028970547794301117 },
      { "token": "line", "score": 0.02778017775349523 },
      { "token": "data", "score": 0.023860102528963888 },
      { "token": "perceiv", "score": 0.02268433778980685 },
      { "token": "graph", "score": 0.02192323957197944 },
      { "token": "effect", "score": 0.020501084903382812 },
      { "token": "angl", "score": 0.019857693879625653 },
      { "token": "tree", "score": 0.019857693879625653 },
      { "token": "among", "score": 0.019857693879625653 },
      { "token": "visual", "score": 0.019710519480448427 },
      { "token": "segment", "score": 0.019313698529534077 },
      { "token": "cleveland", "score": 0.018903614824839043 },
      { "token": "distort", "score": 0.01702088046825056 },
      { "token": "object", "score": 0.016773614920949573 },
      { "token": "accur", "score": 0.015948659917110072 },
      { "token": "graphic", "score": 0.015602473762563011 },
      { "token": "prefer", "score": 0.015122891859871234 },
      { "token": "mcgill", "score": 0.015122891859871234 },
      { "token": "best", "score": 0.014882525807347132 },
      { "token": "imageri", "score": 0.014184067056875466 },
      { "token": "stack", "score": 0.014184067056875466 },
      { "token": "3d", "score": 0.013955077427471312 },
      { "token": "research", "score": 0.013224032569676237 },
      { "token": "compar", "score": 0.013046144938516337 },
      { "token": "appear", "score": 0.012875799019689386 },
      { "token": "conclud", "score": 0.012875799019689386 },
      { "token": "slope", "score": 0.012875799019689386 },
      { "token": "judgment", "score": 0.012875799019689386 },
      { "token": "shape", "score": 0.012765660351187919 },
      { "token": "use", "score": 0.012448749145546376 },
      { "token": "experi", "score": 0.011347253645500373 },
      { "token": "co-author", "score": 0.011342168894903425 },
      { "token": "worst", "score": 0.011342168894903425 },
      { "token": "45", "score": 0.011342168894903425 },
      { "token": "arc", "score": 0.011342168894903425 },
      { "token": "superior", "score": 0.011342168894903425 },
      { "token": "variabl", "score": 0.011182409947299715 },
      { "token": "present", "score": 0.011182409947299715 },
      { "token": "map", "score": 0.010381785639683509 },
      { "token": "two", "score": 0.010373957621288647 },
      { "token": "peopl", "score": 0.010373957621288647 },
      { "token": "rank", "score": 0.01020841254233673 },
      { "token": "increas", "score": 0.01020841254233673 },
      { "token": "engag", "score": 0.01020841254233673 }
    ]
  },
  {
    "id": "binx",
    "day": 26,
    "talk": 4,
    "time": "11:30 - 12:00",
    "speakers": "Rachel Binx",
    "title": "Designing for Realtime Spacecraft Operations",
    "tfidf": [
      { "token": "know", "score": 0.06092342384865878 },
      { "token": "like", "score": 0.05528236608489408 },
      { "token": "evr", "score": 0.04934034414887282 },
      { "token": "data", "score": 0.04851309676837644 },
      { "token": "spacecraft", "score": 0.04522864880313341 },
      { "token": "time", "score": 0.037230981240847026 },
      { "token": "peopl", "score": 0.02933350037157645 },
      { "token": "get", "score": 0.02820528881882351 },
      { "token": "visual", "score": 0.02820528881882351 },
      { "token": "sort", "score": 0.026815243464115186 },
      { "token": "channel", "score": 0.026017258349629056 },
      { "token": "look", "score": 0.025948865713317625 },
      { "token": "record", "score": 0.02567211779851649 },
      { "token": "jpl", "score": 0.02467017207443641 },
      { "token": "thing", "score": 0.023692442607811746 },
      { "token": "go", "score": 0.022564231055058805 },
      { "token": "plan", "score": 0.02100446001696804 },
      { "token": "mission", "score": 0.02100446001696804 },
      { "token": "curios", "score": 0.020558476728697005 },
      { "token": "subsystem", "score": 0.020558476728697005 },
      { "token": "graph", "score": 0.020436382054110705 },
      { "token": "want", "score": 0.020307807949552927 },
      { "token": "event", "score": 0.020268902429729563 },
      { "token": "someth", "score": 0.019179596396799985 },
      { "token": "oh", "score": 0.019160090211448988 },
      { "token": "design", "score": 0.016935943240493804 },
      { "token": "smap", "score": 0.016446781382957604 },
      { "token": "gumbal", "score": 0.016446781382957604 },
      { "token": "alarm", "score": 0.016446781382957604 },
      { "token": "eha", "score": 0.016446781382957604 },
      { "token": "statement", "score": 0.016446781382957604 },
      { "token": "dawn", "score": 0.016446781382957604 },
      { "token": "show", "score": 0.015794961738541165 },
      { "token": "one", "score": 0.015794961738541165 },
      { "token": "chart", "score": 0.015327286540583029 },
      { "token": "differ", "score": 0.014666750185788224 },
      { "token": "day", "score": 0.014113286033744834 },
      { "token": "need", "score": 0.014002973344645361 },
      { "token": "actual", "score": 0.014002973344645361 },
      { "token": "would", "score": 0.014002973344645361 },
      { "token": "nasa", "score": 0.014002973344645358 },
      { "token": "okay", "score": 0.013785934721249926 },
      { "token": "think", "score": 0.013538538633035285 },
      { "token": "work", "score": 0.013538538633035285 },
      { "token": "come", "score": 0.013538538633035285 },
      { "token": "realli", "score": 0.013538538633035285 },
      { "token": "built", "score": 0.013333021515888391 },
      { "token": "could", "score": 0.012836058899258245 },
      { "token": "drive", "score": 0.012660584147948436 },
      { "token": "art", "score": 0.012660584147948436 }
    ]
  },
  {
    "id": "satyanarayan",
    "day": 26,
    "talk": 5,
    "time": "12:00 - 12:30",
    "speakers": "Arvind Satyanarayan",
    "title": "Reactive Building Blocks: Interactive Visualizations with Vega",
    "tfidf": [
      { "token": "vega", "score": 0.10338132664601456 },
      { "token": "brush", "score": 0.09631465079359017 },
      { "token": "event", "score": 0.06669735705782885 },
      { "token": "signal", "score": 0.06247436808232875 },
      { "token": "data", "score": 0.04759642488176467 },
      { "token": "stream", "score": 0.04059299792435967 },
      { "token": "interact", "score": 0.03855046996870866 },
      { "token": "valu", "score": 0.029653589463500017 },
      { "token": "json", "score": 0.028634085371067347 },
      { "token": "know", "score": 0.027605926431423507 },
      { "token": "lite", "score": 0.026583769708975174 },
      { "token": "visual", "score": 0.02570206943615292 },
      { "token": "mous", "score": 0.02563768289959558 },
      { "token": "scatterplot", "score": 0.023942640995118048 },
      { "token": "use", "score": 0.023798212440882337 },
      { "token": "highlight", "score": 0.023427888030873284 },
      { "token": "start", "score": 0.022645433455793666 },
      { "token": "select", "score": 0.022126338695824768 },
      { "token": "drag", "score": 0.021952061732499514 },
      { "token": "sort", "score": 0.02143455316374997 },
      { "token": "predic", "score": 0.020815457687805718 },
      { "token": "like", "score": 0.019990498450341163 },
      { "token": "particular", "score": 0.019718647997184133 },
      { "token": "exampl", "score": 0.019373517144681846 },
      { "token": "wikipedia", "score": 0.01873475710894752 },
      { "token": "point", "score": 0.01870709720261216 },
      { "token": "build", "score": 0.01865345321066548 },
      { "token": "techniqu", "score": 0.01820182892047766 },
      { "token": "mark", "score": 0.017722513139316783 },
      { "token": "declar", "score": 0.0173462147398381 },
      { "token": "one", "score": 0.01713471295743528 },
      { "token": "want", "score": 0.01713471295743528 },
      { "token": "design", "score": 0.016671319127361087 },
      { "token": "fall", "score": 0.016464046299374636 },
      { "token": "coordin", "score": 0.01575334501272603 },
      { "token": "scale", "score": 0.015618592020582188 },
      { "token": "specifi", "score": 0.015618592020582188 },
      { "token": "detail", "score": 0.015391697782575889 },
      { "token": "see", "score": 0.015230855962164695 },
      { "token": "within", "score": 0.015168190767064717 },
      { "token": "specif", "score": 0.014922762568532384 },
      { "token": "devic", "score": 0.014768760949430651 },
      { "token": "callback", "score": 0.014768760949430651 },
      { "token": "histogram", "score": 0.014634707821666343 },
      { "token": "matrix", "score": 0.014051067831710638 },
      { "token": "hood", "score": 0.013876971791870479 },
      { "token": "also", "score": 0.013784176886135275 },
      { "token": "filter", "score": 0.013651371690358247 },
      { "token": "way", "score": 0.013326998966894108 },
      { "token": "go", "score": 0.013326998966894108 }
    ]
  },
  {
    "id": "pearce",
    "day": 26,
    "talk": 6,
    "time": "2:00 - 2:30",
    "speakers": "Adam Pearce",
    "title": "Tiny Tools",
    "tfidf": [
      { "token": "librari", "score": 0.043022928448548325 },
      { "token": "thing", "score": 0.04275143708000711 },
      { "token": "like", "score": 0.03812966009838472 },
      { "token": "make", "score": 0.03812966009838472 },
      { "token": "code", "score": 0.0316980060076412 },
      { "token": "d3", "score": 0.031394511052090755 },
      { "token": "work", "score": 0.030041550380545533 },
      { "token": "stepper", "score": 0.029476602151007638 },
      { "token": "svg", "score": 0.028865699565493615 },
      { "token": "page", "score": 0.02761656801727645 },
      { "token": "sort", "score": 0.024571717649785402 },
      { "token": "function", "score": 0.02283396697859534 },
      { "token": "scroll", "score": 0.02211736249351409 },
      { "token": "one", "score": 0.020797996417300756 },
      { "token": "last", "score": 0.01925277090381455 },
      { "token": "html", "score": 0.01895773928015493 },
      { "token": "css", "score": 0.01895773928015493 },
      { "token": "time", "score": 0.018487107926489558 },
      { "token": "realli", "score": 0.018487107926489558 },
      { "token": "translat", "score": 0.017926220186895134 },
      { "token": "data", "score": 0.01733166368108396 },
      { "token": "framework", "score": 0.01705508923021429 },
      { "token": "transform", "score": 0.01705508923021429 },
      { "token": "coupl", "score": 0.01656994081036587 },
      { "token": "start", "score": 0.015536057495309119 },
      { "token": "use", "score": 0.015020775190272766 },
      { "token": "bunch", "score": 0.014918449145502798 },
      { "token": "line", "score": 0.014851857789316898 },
      { "token": "would", "score": 0.01434097614951611 },
      { "token": "margin", "score": 0.014340976149516108 },
      { "token": "stuff", "score": 0.0142183044601162 },
      { "token": "copi", "score": 0.01421257435851191 },
      { "token": "want", "score": 0.01386533094486717 },
      { "token": "publish", "score": 0.013654853069720179 },
      { "token": "instead", "score": 0.013584859717560514 },
      { "token": "project", "score": 0.013330860141956584 },
      { "token": "talk", "score": 0.0131458948037231 },
      { "token": "flexibl", "score": 0.01296618445496788 },
      { "token": "get", "score": 0.012709886699461572 },
      { "token": "graphic", "score": 0.012638492853436621 },
      { "token": "scale", "score": 0.012638492853436621 },
      { "token": "adam", "score": 0.012632829493288988 },
      { "token": "bloomberg", "score": 0.012632829493288988 },
      { "token": "great", "score": 0.011997774127760926 },
      { "token": "month", "score": 0.011704159774045868 },
      { "token": "think", "score": 0.011554442454055975 },
      { "token": "go", "score": 0.011554442454055975 },
      { "token": "script", "score": 0.011370059486809529 },
      { "token": "modifi", "score": 0.011370059486809529 },
      { "token": "format", "score": 0.011102192140574467 }
    ]
  },
  {
    "id": "hullman",
    "day": 26,
    "talk": 7,
    "time": "2:30 - 3:00",
    "speakers": "Jessica Hullman",
    "title": "The Visual Uncertainty Experience",
    "tfidf": [
      { "token": "uncertainti", "score": 0.13751145678850527 },
      { "token": "distribut", "score": 0.10104681898761371 },
      { "token": "peopl", "score": 0.05620677167973036 },
      { "token": "height", "score": 0.0547452634592468 },
      { "token": "poll", "score": 0.05030906955677022 },
      { "token": "sampl", "score": 0.04786428267834334 },
      { "token": "visual", "score": 0.04539777712593606 },
      { "token": "show", "score": 0.04107417930441833 },
      { "token": "probabl", "score": 0.03426390184717432 },
      { "token": "error", "score": 0.03396303799172232 },
      { "token": "static", "score": 0.033539379704513476 },
      { "token": "one", "score": 0.0324269836613829 },
      { "token": "treatment", "score": 0.031514155295086506 },
      { "token": "candid", "score": 0.030185441734062134 },
      { "token": "sort", "score": 0.029747164820802825 },
      { "token": "thing", "score": 0.029184285295244607 },
      { "token": "like", "score": 0.029184285295244607 },
      { "token": "want", "score": 0.029184285295244607 },
      { "token": "random", "score": 0.02906746241057835 },
      { "token": "use", "score": 0.02810338583986518 },
      { "token": "bar", "score": 0.02791193711094072 },
      { "token": "data", "score": 0.027022486384485747 },
      { "token": "measur", "score": 0.026831503763610785 },
      { "token": "plot", "score": 0.02610582997879948 },
      { "token": "differ", "score": 0.02377978801834746 },
      { "token": "know", "score": 0.02377978801834746 },
      { "token": "see", "score": 0.02377978801834746 },
      { "token": "reliabl", "score": 0.02363561647131488 },
      { "token": "music", "score": 0.023477565793159433 },
      { "token": "look", "score": 0.02269888856296803 },
      { "token": "possibl", "score": 0.02118069525856209 },
      { "token": "outcom", "score": 0.02069043588102931 },
      { "token": "think", "score": 0.020537089652209167 },
      { "token": "experienc", "score": 0.020123627822708087 },
      { "token": "studi", "score": 0.019579372484099612 },
      { "token": "could", "score": 0.019005648499224308 },
      { "token": "variat", "score": 0.01861388770824463 },
      { "token": "et", "score": 0.01861388770824463 },
      { "token": "cetera", "score": 0.01861388770824463 },
      { "token": "way", "score": 0.01837529074145031 },
      { "token": "time", "score": 0.01837529074145031 },
      { "token": "go", "score": 0.01837529074145031 },
      { "token": "bin", "score": 0.01773465932659655 },
      { "token": "mean", "score": 0.017367091769765728 },
      { "token": "instanc", "score": 0.016769689852256738 },
      { "token": "14", "score": 0.016769689852256738 },
      { "token": "aggreg", "score": 0.01661747468782759 },
      { "token": "answer", "score": 0.01642357903777404 },
      { "token": "get", "score": 0.01621349183069145 },
      { "token": "folk", "score": 0.015954760892781115 }
    ]
  },
  {
    "id": "albrecht",
    "day": 26,
    "talk": 8,
    "time": "3:00 - 3:30",
    "speakers": "Kim Albrecht",
    "title": "Untangling Tennis",
    "tfidf": [
      { "token": "like", "score": 0.07119457844670056 },
      { "token": "player", "score": 0.059252056564610495 },
      { "token": "model", "score": 0.05425518212478021 },
      { "token": "tournament", "score": 0.05076471897996036 },
      { "token": "view", "score": 0.046856748198673824 },
      { "token": "page", "score": 0.0419244589146029 },
      { "token": "tenni", "score": 0.03948367031774695 },
      { "token": "rank", "score": 0.03426773124777467 },
      { "token": "predict", "score": 0.030585914197656574 },
      { "token": "play", "score": 0.029626028282305247 },
      { "token": "galaxi", "score": 0.028202621655533538 },
      { "token": "sport", "score": 0.028202621655533538 },
      { "token": "wikipedia", "score": 0.026652679859380305 },
      { "token": "one", "score": 0.026311039860737163 },
      { "token": "actual", "score": 0.02561282884286172 },
      { "token": "career", "score": 0.025393738527690213 },
      { "token": "data", "score": 0.023215623406532788 },
      { "token": "see", "score": 0.021667915179430605 },
      { "token": "perform", "score": 0.020819815284402927 },
      { "token": "differ", "score": 0.02012020695232842 },
      { "token": "success", "score": 0.019729157136283714 },
      { "token": "chart", "score": 0.018690086128008866 },
      { "token": "person", "score": 0.01819680978333741 },
      { "token": "physicist", "score": 0.016921572993320123 },
      { "token": "interfac", "score": 0.016683225925994496 },
      { "token": "yeah", "score": 0.016174942029633252 },
      { "token": "also", "score": 0.016008018026788574 },
      { "token": "network", "score": 0.016008018026788574 },
      { "token": "look", "score": 0.01547708227102186 },
      { "token": "work", "score": 0.01547708227102186 },
      { "token": "got", "score": 0.015473358601680054 },
      { "token": "scientist", "score": 0.015230102776788745 },
      { "token": "popular", "score": 0.015230102776788745 },
      { "token": "icon", "score": 0.014407216224109717 },
      { "token": "good", "score": 0.014407216224109716 },
      { "token": "point", "score": 0.014407216224109716 },
      { "token": "connect", "score": 0.01390268827166208 },
      { "token": "compar", "score": 0.01390268827166208 },
      { "token": "okay", "score": 0.013754096534826716 },
      { "token": "sort", "score": 0.01355266589568384 },
      { "token": "final", "score": 0.013322094694983253 },
      { "token": "creat", "score": 0.01280641442143086 },
      { "token": "known", "score": 0.012696869263845107 },
      { "token": "round", "score": 0.012696869263845107 },
      { "token": "thing", "score": 0.012381665816817489 },
      { "token": "someth", "score": 0.012381665816817489 },
      { "token": "go", "score": 0.012381665816817489 },
      { "token": "visual", "score": 0.012381665816817489 },
      { "token": "articl", "score": 0.011897037305373101 },
      { "token": "lab", "score": 0.011897037305373101 }
    ]
  },
  {
    "id": "waigl",
    "day": 26,
    "talk": 9,
    "time": "4:00 - 4:45",
    "speakers": "Christine Waigl",
    "title": "Our Planet Seen from Space",
    "tfidf": [
      { "token": "satellit", "score": 0.07659607315873883 },
      { "token": "data", "score": 0.049370414414874914 },
      { "token": "one", "score": 0.032913609609916614 },
      { "token": "ice", "score": 0.0299878899294991 },
      { "token": "imag", "score": 0.02743427065723635 },
      { "token": "landsat", "score": 0.026655902159554754 },
      { "token": "want", "score": 0.023770940273828665 },
      { "token": "fire", "score": 0.022571420688320624 },
      { "token": "see", "score": 0.021942406406611072 },
      { "token": "use", "score": 0.020113872539393486 },
      { "token": "someth", "score": 0.020113872539393486 },
      { "token": "thing", "score": 0.020113872539393486 },
      { "token": "pole", "score": 0.020000889099572282 },
      { "token": "imageri", "score": 0.020000889099572282 },
      { "token": "river", "score": 0.019991926619666065 },
      { "token": "glacier", "score": 0.019991926619666065 },
      { "token": "orbit", "score": 0.01985824118930266 },
      { "token": "map", "score": 0.019442832519611916 },
      { "token": "get", "score": 0.019199605605784688 },
      { "token": "librari", "score": 0.018912610656478725 },
      { "token": "band", "score": 0.017500777962125746 },
      { "token": "meta", "score": 0.01702134959083085 },
      { "token": "alaska", "score": 0.01702134959083085 },
      { "token": "smoke", "score": 0.016659938849721723 },
      { "token": "raster", "score": 0.016659938849721723 },
      { "token": "leaflet", "score": 0.016659938849721723 },
      { "token": "work", "score": 0.01554253787134951 },
      { "token": "need", "score": 0.01513008852518298 },
      { "token": "python", "score": 0.01500066682467921 },
      { "token": "know", "score": 0.014628270937740715 },
      { "token": "town", "score": 0.014184457992359043 },
      { "token": "north", "score": 0.014184457992359043 },
      { "token": "burn", "score": 0.014184457992359043 },
      { "token": "realli", "score": 0.013714004004131922 },
      { "token": "like", "score": 0.013714004004131922 },
      { "token": "littl", "score": 0.013710446253894181 },
      { "token": "gdal", "score": 0.013327951079777377 },
      { "token": "fairbank", "score": 0.013327951079777377 },
      { "token": "sea", "score": 0.013327951079777377 },
      { "token": "flood", "score": 0.013327951079777377 },
      { "token": "sentinel", "score": 0.013327951079777377 },
      { "token": "portal", "score": 0.013327951079777377 },
      { "token": "good", "score": 0.013238827459535108 },
      { "token": "earlier", "score": 0.013238827459535108 },
      { "token": "combin", "score": 0.013111276493877496 },
      { "token": "lot", "score": 0.012799737070523126 },
      { "token": "make", "score": 0.012799737070523126 },
      { "token": "go", "score": 0.012799737070523126 },
      { "token": "exampl", "score": 0.012731128664330313 },
      { "token": "bit", "score": 0.012580656336219475 }
    ]
  },
  {
    "id": "collins",
    "day": 26,
    "talk": 10,
    "time": "4:45 - 5:15",
    "speakers": "Christopher Collins",
    "title": "Finding What to Read: Visual Text Analytics Tools and Techniques to Guide Investigation",
    "tfidf": [
      { "token": "password", "score": 0.055328249992182624 },
      { "token": "word", "score": 0.041467998536981916 },
      { "token": "barbi", "score": 0.036885499994788414 },
      { "token": "court", "score": 0.03364792138640511 },
      { "token": "car", "score": 0.03360721130930019 },
      { "token": "tweet", "score": 0.029161531868217763 },
      { "token": "document", "score": 0.028413800281853207 },
      { "token": "look", "score": 0.027471403634023055 },
      { "token": "use", "score": 0.02530260861028439 },
      { "token": "thing", "score": 0.024579676935704835 },
      { "token": "see", "score": 0.023856745261125283 },
      { "token": "anomali", "score": 0.02243194759093674 },
      { "token": "interest", "score": 0.018470475645946505 },
      { "token": "district", "score": 0.018442749997394207 },
      { "token": "get", "score": 0.01807329186448885 },
      { "token": "text", "score": 0.017460209910308173 },
      { "token": "visual", "score": 0.017350360189909295 },
      { "token": "data", "score": 0.017350360189909295 },
      { "token": "one", "score": 0.016627428515329744 },
      { "token": "english", "score": 0.015815158263200086 },
      { "token": "accid", "score": 0.015815158263200086 },
      { "token": "retweet", "score": 0.015808071426337892 },
      { "token": "rumor", "score": 0.015808071426337892 },
      { "token": "talk", "score": 0.01570236331365572 },
      { "token": "peopl", "score": 0.015181565166170634 },
      { "token": "like", "score": 0.015181565166170634 },
      { "token": "love", "score": 0.014519694002335217 },
      { "token": "go", "score": 0.01445863349159108 },
      { "token": "drill", "score": 0.014227906153936409 },
      { "token": "inform", "score": 0.013565197255735326 },
      { "token": "relat", "score": 0.013459168554562043 },
      { "token": "hurrican", "score": 0.013173392855281577 },
      { "token": "linguist", "score": 0.013173392855281577 },
      { "token": "read", "score": 0.01301574135388624 },
      { "token": "differ", "score": 0.01301277014243197 },
      { "token": "work", "score": 0.01301277014243197 },
      { "token": "bit", "score": 0.012660850772019639 },
      { "token": "project", "score": 0.012511163240023979 },
      { "token": "exampl", "score": 0.012389899342400288 },
      { "token": "report", "score": 0.011963705381832928 },
      { "token": "find", "score": 0.01161553063350027 },
      { "token": "time", "score": 0.011566906793272862 },
      { "token": "realli", "score": 0.011566906793272862 },
      { "token": "date", "score": 0.01121597379546837 },
      { "token": "collabor", "score": 0.01121597379546837 },
      { "token": "languag", "score": 0.01091263119394261 },
      { "token": "level", "score": 0.010852157804588262 },
      { "token": "toyota", "score": 0.01053871428422526 },
      { "token": "fashion", "score": 0.010468242209103813 },
      { "token": "book", "score": 0.010390272313492436 }
    ]
  },
  {
    "id": "becker",
    "day": 26,
    "talk": 11,
    "time": "5:15 - 5:45",
    "speakers": "Designing Virtual Reality Data Visualizations",
    "title": "Ana Asnes Becker",
    "tfidf": [
      { "token": "vr", "score": 0.10886430584010019 },
      { "token": "nasdaq", "score": 0.04259907619830008 },
      { "token": "like", "score": 0.03766389962736851 },
      { "token": "realli", "score": 0.033767634148675216 },
      { "token": "cardboard", "score": 0.03313261482090006 },
      { "token": "go", "score": 0.032468878989110786 },
      { "token": "peopl", "score": 0.029871368669981923 },
      { "token": "thing", "score": 0.02727385835085306 },
      { "token": "feel", "score": 0.024221599172500236 },
      { "token": "3d", "score": 0.022462574796046013 },
      { "token": "walk", "score": 0.022365523990526496 },
      { "token": "journal", "score": 0.022365523990526496 },
      { "token": "coolest", "score": 0.020149627341858874 },
      { "token": "shit", "score": 0.020149627341858874 },
      { "token": "video", "score": 0.0199667331520409 },
      { "token": "sort", "score": 0.01949602768382426 },
      { "token": "get", "score": 0.019481327393466467 },
      { "token": "make", "score": 0.019481327393466467 },
      { "token": "headset", "score": 0.018932922754800033 },
      { "token": "right", "score": 0.018806318852401617 },
      { "token": "think", "score": 0.016883817074337608 },
      { "token": "cool", "score": 0.015981815090828286 },
      { "token": "chart", "score": 0.015683735064782635 },
      { "token": "look", "score": 0.014286306755208743 },
      { "token": "see", "score": 0.014286306755208743 },
      { "token": "kid", "score": 0.014206057858514032 },
      { "token": "roger", "score": 0.014199692066100025 },
      { "token": "360-degre", "score": 0.014199692066100025 },
      { "token": "hack", "score": 0.014199692066100025 },
      { "token": "googl", "score": 0.013723268181684805 },
      { "token": "ever", "score": 0.013155838505710471 },
      { "token": "kind", "score": 0.012987551595644313 },
      { "token": "lot", "score": 0.012987551595644313 },
      { "token": "one", "score": 0.012987551595644313 },
      { "token": "path", "score": 0.012780299423157997 },
      { "token": "man", "score": 0.012780299423157997 },
      { "token": "button", "score": 0.012780299423157997 },
      { "token": "empathi", "score": 0.012089776405115323 },
      { "token": "wall", "score": 0.012089776405115323 },
      { "token": "oh", "score": 0.011876513878831974 },
      { "token": "render", "score": 0.011666403142693179 },
      { "token": "5", "score": 0.011659514703692048 },
      { "token": "content", "score": 0.011659514703692048 },
      { "token": "browser", "score": 0.010746467915658066 },
      { "token": "danger", "score": 0.010746467915658066 },
      { "token": "stuff", "score": 0.010654543393885524 },
      { "token": "red", "score": 0.010654543393885524 },
      { "token": "price", "score": 0.010654543393885524 },
      { "token": "navig", "score": 0.010654543393885524 },
      { "token": "use", "score": 0.01039004127651545 }
    ]
  }
]